guillotina_fhirfield/__init__.py
guillotina_fhirfield/cli.py
guillotina_fhirfield/exc.py
guillotina_fhirfield/field.py
guillotina_fhirfield/helpers.py
guillotina_fhirfield/interfaces.py
guillotina_fhirfield/patch.py
guillotina_fhirfield/variables.py
guillotina_fhirfield/static/.gitkeep
guillotina_fhirfield/static/HL7/FHIR/ResourceList/STU3.json
guillotina_fhirfield/static/HL7/FHIR/search/FHIR-Search-Parameter-Registry-searchable.json
guillotina_fhirfield/static/HL7/FHIR/search/FHIR-Search-Parameter-Registry.json
guillotina_fhirfield/tests/__init__.py
guillotina_fhirfield/tests/conftest.py
guillotina_fhirfield/tests/fhir_contents.py
guillotina_fhirfield/tests/fixtures.py
guillotina_fhirfield/tests/helpers.py
guillotina_fhirfield/tests/test_field.py
guillotina_fhirfield/tests/test_guillotina_fhirfield.py
guillotina_fhirfield/tests/static/FHIR/ChargeItem.json
guillotina_fhirfield/tests/static/FHIR/Encounter.json
guillotina_fhirfield/tests/static/FHIR/Media.json
guillotina_fhirfield/tests/static/FHIR/MedicationRequest.json
guillotina_fhirfield/tests/static/FHIR/Observation.json
guillotina_fhirfield/tests/static/FHIR/Organization.json
guillotina_fhirfield/tests/static/FHIR/ParentTask.json
guillotina_fhirfield/tests/static/FHIR/Patient.json
guillotina_fhirfield/tests/static/FHIR/Practitioner.json
guillotina_fhirfield/tests/static/FHIR/ProcedureRequest_HAQ.json
guillotina_fhirfield/tests/static/FHIR/ProcedureRequest_JOINT.json
guillotina_fhirfield/tests/static/FHIR/SubTask_CRP.json
guillotina_fhirfield/tests/static/FHIR/SubTask_HAQ.json
guillotina_fhirfield-0.1.0a1.dist-info/AUTHORS.rst
guillotina_fhirfield-0.1.0a1.dist-info/LICENSE
guillotina_fhirfield-0.1.0a1.dist-info/METADATA
guillotina_fhirfield-0.1.0a1.dist-info/WHEEL
guillotina_fhirfield-0.1.0a1.dist-info/entry_points.txt
guillotina_fhirfield-0.1.0a1.dist-info/top_level.txt
guillotina_fhirfield-0.1.0a1.dist-info/RECORD
