Metadata-Version: 2.1
Name: guillotina-fhirfield
Version: 0.1.0a1
Summary: FHIR field for guillotina.
Home-page: https://github.com/nazrulworld/guillotina_fhirfield
Author: Md Nazrul Islam
Author-email: email2nazrul@gmail.com
License: BSD license
Keywords: guillotina_fhirfield
Platform: UNKNOWN
Classifier: Development Status :: 2 - Pre-Alpha
Classifier: Intended Audience :: Developers
Classifier: License :: OSI Approved :: BSD License
Classifier: Natural Language :: English
Classifier: Programming Language :: Python :: 3
Classifier: Programming Language :: Python :: 3.6
Classifier: Programming Language :: Python :: 3.7
Requires-Dist: Click (>=6.0)
Requires-Dist: guillotina (>=4.3.5)
Requires-Dist: fhirclient
Requires-Dist: jsonpatch
Provides-Extra: test
Requires-Dist: coverage ; extra == 'test'
Requires-Dist: docker ; extra == 'test'
Requires-Dist: pytest ; extra == 'test'
Requires-Dist: pytest-asyncio ; extra == 'test'
Requires-Dist: pytest-cov ; extra == 'test'
Requires-Dist: pytest-isort ; extra == 'test'
Requires-Dist: pytest-docker-fixtures ; extra == 'test'
Requires-Dist: tox-pipenv ; extra == 'test'
Requires-Dist: pytest-runner ; extra == 'test'
